twobodyproblem_gui/__init__.py
twobodyproblem_gui/__main__.py
twobodyproblem_gui/entry.py
twobodyproblem_gui/examples.py
twobodyproblem_gui/settings.py
twobodyproblem_gui/ui/entry.ui
twobodyproblem_gui/ui/examples.ui
twobodyproblem_gui/ui/icon.gif
twobodyproblem_gui/ui/settings.ui
twobodyproblem_gui-1.0.0.dist-info/LICENSE.md
twobodyproblem_gui-1.0.0.dist-info/METADATA
twobodyproblem_gui-1.0.0.dist-info/WHEEL
twobodyproblem_gui-1.0.0.dist-info/top_level.txt
twobodyproblem_gui-1.0.0.dist-info/RECORD
