Metadata-Version: 2.1
Name: twobodyproblem-gui
Version: 1.0.0
Summary: a graphical user interface for the package twobodyproblem
Home-page: https://github.com/Two-Body-Problem/twobodyproblem-simulation-python-gui
Author: Florian Frauenfelder
Author-email: florian.l.frauenfelder@gmail.com
License: MIT
Keywords: pyside
Platform: UNKNOWN
Classifier: Development Status :: 5 - Production/Stable
Classifier: Environment :: X11 Applications :: Qt
Classifier: Intended Audience :: End Users/Desktop
Classifier: License :: OSI Approved :: MIT License
Classifier: Natural Language :: German
Classifier: Operating System :: OS Independent
Classifier: Programming Language :: Python :: 3 :: Only
Classifier: Programming Language :: Python :: 3.8
Classifier: Programming Language :: Python :: 3.9
Requires-Python: >=3.8
Requires-Dist: pyside6
Requires-Dist: twobodyproblem (>=2.0.0)
